cfsign/__init__.py
cfsign/py.typed
cfsign/config/__init__.py
cfsign/config/cfsign_config.py
cfsign/exceptions/__init__.py
cfsign/exceptions/base_cfsign_error.py
cfsign/exceptions/cloudfront_signature_errors.py
cfsign/exceptions/configuration_errors.py
cfsign/signature/__init__.py
cfsign/signature/cloudfront_signature.py
cfsign/types/__init__.py
cfsign/types/cloudfront_signature_types.py
cfsign/utils/__init__.py
cfsign/utils/configure.py
cfsign-0.0.3.dist-info/METADATA
cfsign-0.0.3.dist-info/WHEEL
cfsign-0.0.3.dist-info/top_level.txt
cfsign-0.0.3.dist-info/RECORD
