Metadata-Version: 2.4
Name: cfsign
Version: 0.0.3
Summary: A simple library for creating CloudFront signatures
Requires-Python: <4.0,>=3.8
Requires-Dist: cryptography>=44.0.2
Requires-Dist: typing-extensions>=4.13.2
